apexbase/__init__.py
apexbase/_core.cpython-313-darwin.so
apexbase/client.py
apexbase-0.4.0.dist-info/METADATA
apexbase-0.4.0.dist-info/WHEEL
apexbase-0.4.0.dist-info/licenses/LICENSE
apexbase-0.4.0.dist-info/RECORD
