Metadata-Version: 2.4
Name: apexbase
Version: 0.4.0
Classifier: Development Status :: 4 - Beta
Classifier: Intended Audience :: Developers
Classifier: License :: OSI Approved :: Apache Software License
Classifier: Programming Language :: Python :: 3
Classifier: Programming Language :: Python :: 3.9
Classifier: Programming Language :: Python :: 3.10
Classifier: Programming Language :: Python :: 3.11
Classifier: Programming Language :: Python :: 3.12
Classifier: Programming Language :: Python :: 3.13
Classifier: Programming Language :: Rust
Classifier: Topic :: Database
Requires-Dist: nanofts>=0.1.0
Requires-Dist: pyarrow>=10.0.0
Requires-Dist: pandas>=2.0.0
Requires-Dist: polars>=0.15.0
Requires-Dist: pytest>=7.0.0 ; extra == 'dev'
Requires-Dist: maturin>=1.4.0 ; extra == 'dev'
Provides-Extra: dev
License-File: LICENSE
Summary: High-performance embedded database with Rust core and Python API
Keywords: database,embedded-database,rust,high-performance
Author-email: Birch Kwok <birchkwok@gmail.com>
License: Apache-2.0
Requires-Python: >=3.9
Project-URL: Homepage, https://github.com/BirchKwok/ApexBase
Project-URL: Repository, https://github.com/BirchKwok/ApexBase
